wagtail_xliff_translation/__init__.py
wagtail_xliff_translation/apps.py
wagtail_xliff_translation/constants.py
wagtail_xliff_translation/forms.py
wagtail_xliff_translation/utils.py
wagtail_xliff_translation/views.py
wagtail_xliff_translation/wagtail_hooks.py
wagtail_xliff_translation/xliff_generator.py
wagtail_xliff_translation/helpers/Translation.py
wagtail_xliff_translation/helpers/__init__.py
wagtail_xliff_translation/helpers/page.py
wagtail_xliff_translation/parsers/__init__.py
wagtail_xliff_translation/parsers/html_xliff.py
wagtail_xliff_translation/parsers/xliff_wagtail.py
wagtail_xliff_translation/serializers/__init__.py
wagtail_xliff_translation/serializers/wagtail_xliff.py
wagtail_xliff_translation/serializers/xliff_wagtail.py
wagtail_xliff_translation/templates/xliff/admin/download.html
wagtail_xliff_translation/templates/xliff/admin/import.html
wagtail_xliff_translation/test_app/__init__.py
wagtail_xliff_translation/test_app/apps.py
wagtail_xliff_translation/test_app/asgi.py
wagtail_xliff_translation/test_app/blocks.py
wagtail_xliff_translation/test_app/models.py
wagtail_xliff_translation/test_app/settings.py
wagtail_xliff_translation/test_app/urls.py
wagtail_xliff_translation/test_app/wsgi.py
wagtail_xliff_translation/test_app/factories/__init__.py
wagtail_xliff_translation/test_app/factories/page_factories.py
wagtail_xliff_translation/test_app/migrations/0001_initial.py
wagtail_xliff_translation/test_app/migrations/__init__.py
wagtail_xliff_translation/tests/__init__.py
wagtail_xliff_translation/tests/conftest.py
wagtail_xliff_translation/tests/utils.py
wagtail_xliff_translation/tests/functional/__init__.py
wagtail_xliff_translation/tests/functional/test_integration.py
wagtail_xliff_translation/tests/functional/test_views.py
wagtail_xliff_translation/tests/functional/test_wagtail_hooks.py
wagtail_xliff_translation/tests/functional/test_wagtail_xliff.py
wagtail_xliff_translation/tests/functional/test_xliff_wagtail.py
wagtail_xliff_translation-1.0.4.dist-info/LICENSE
wagtail_xliff_translation-1.0.4.dist-info/METADATA
wagtail_xliff_translation-1.0.4.dist-info/WHEEL
wagtail_xliff_translation-1.0.4.dist-info/top_level.txt
wagtail_xliff_translation-1.0.4.dist-info/RECORD
