Metadata-Version: 2.1
Name: wagtail-xliff-translation
Version: 1.0.4
Summary: Export Wagtail content to XLIFF and back
Home-page: https://github.com/fourdigits/wagtail-xliff-translation
Author: Lennard de Vries
Author-email: lennard@fourdigits.nl
License: UNKNOWN
Project-URL: Projects, https://github.com/fourdigits/wagtail-xliff-translation/projects
Project-URL: Bug Tracker, https://github.com/fourdigits/wagtail-xliff-translation/issues
Platform: UNKNOWN
Classifier: Environment :: Web Environment
Classifier: Intended Audience :: Developers
Classifier: License :: OSI Approved :: BSD License
Classifier: Operating System :: OS Independent
Classifier: Programming Language :: Python
Classifier: Programming Language :: Python :: 3
Classifier: Programming Language :: Python :: 3.6
Classifier: Programming Language :: Python :: 3.7
Classifier: Programming Language :: Python :: 3.8
Classifier: Programming Language :: Python :: 3.9
Classifier: Framework :: Django
Classifier: Framework :: Wagtail
Classifier: Framework :: Wagtail :: 2
Requires-Python: >=3.6
License-File: LICENSE
Requires-Dist: wagtail
Provides-Extra: docs
Requires-Dist: mkdocs (<1.2,>=1.1) ; extra == 'docs'
Requires-Dist: mkdocs-material (<7.2,>=7.1) ; extra == 'docs'
Provides-Extra: test
Requires-Dist: django-extensions ; extra == 'test'
Requires-Dist: factory-boy ; extra == 'test'
Requires-Dist: pytest ; extra == 'test'
Requires-Dist: pytest-black ; extra == 'test'
Requires-Dist: pytest-cov ; extra == 'test'
Requires-Dist: pytest-django ; extra == 'test'
Requires-Dist: pytest-mock ; extra == 'test'
Requires-Dist: pytest-factoryboy ; extra == 'test'
Requires-Dist: pytest-flake8 ; extra == 'test'
Requires-Dist: pytest-isort ; extra == 'test'
Requires-Dist: pytest-mccabe ; extra == 'test'
Requires-Dist: wagtail-factories ; extra == 'test'
